MANIFEST.in
README.md
requirements.txt
setup.py
gh_archiver/__init__.py
gh_archiver.egg-info/PKG-INFO
gh_archiver.egg-info/SOURCES.txt
gh_archiver.egg-info/dependency_links.txt
gh_archiver.egg-info/entry_points.txt
gh_archiver.egg-info/requires.txt
gh_archiver.egg-info/top_level.txt
gh_archiver.egg-info/zip-safe