Metadata-Version: 1.0
Name: gh-archiver
Version: 0.0.3
Summary: Clone and update a GitHub user's repos locally.
Home-page: https://github.com/ChrisCummins/gh-archiver
Author: Chris Cummins
Author-email: chrisc.101@gmail.com
License: MIT License
Platform: UNKNOWN
